fpscanner/__init__.py
fpscanner/communication/CommunicationException.py
fpscanner/communication/RqCommand.py
fpscanner/communication/RqPackage.py
fpscanner/communication/RqSimple.py
fpscanner/communication/RsBytes.py
fpscanner/communication/RsCached.py
fpscanner/communication/RsCheckHeader.py
fpscanner/communication/RsCheckSum.py
fpscanner/communication/RsDataPacket.py
fpscanner/communication/RsPackage.py
fpscanner/communication/RsSimple.py
fpscanner/communication/__init__.py
fpscanner/communication/port/LoggablePort.py
fpscanner/communication/port/Port.py
fpscanner/communication/port/SerialPort.py
fpscanner/communication/port/__init__.py
fpscanner/communication/rqbuffer/RqCharBuffer.py
fpscanner/communication/rqbuffer/RqCharBuffer1.py
fpscanner/communication/rqbuffer/RqCharBuffer2.py
fpscanner/communication/rqbuffer/__init__.py
fpscanner/communication/rqpid/RqPid.py
fpscanner/communication/rqpid/RqPidCommand.py
fpscanner/communication/rqpid/__init__.py
fpscanner/communication/rqprimitives/RqByte.py
fpscanner/communication/rqprimitives/RqBytes.py
fpscanner/communication/rqprimitives/RqDword.py
fpscanner/communication/rqprimitives/RqGroup.py
fpscanner/communication/rqprimitives/RqWord.py
fpscanner/communication/rqprimitives/__init__.py
fpscanner/communication/rsprimitives/RsDword.py
fpscanner/communication/rsprimitives/RsWord.py
fpscanner/communication/rsprimitives/__init__.py
fpscanner/instructions/ConfirmationCode.py
fpscanner/instructions/Handshake.py
fpscanner/instructions/InstructionException.py
fpscanner/instructions/Search.py
fpscanner/instructions/VerifyPassword.py
fpscanner/instructions/__init__.py
fpscanner/instructions/characteristic/LoadChar.py
fpscanner/instructions/characteristic/Match.py
fpscanner/instructions/characteristic/RegModel.py
fpscanner/instructions/characteristic/UpChar.py
fpscanner/instructions/characteristic/__init__.py
fpscanner/instructions/image/Img2Tz.py
fpscanner-0.1.1.dist-info/METADATA
fpscanner-0.1.1.dist-info/RECORD
fpscanner-0.1.1.dist-info/WHEEL
fpscanner-0.1.1.dist-info/top_level.txt
