Metadata-Version: 2.1
Name: fpscanner
Version: 0.1.1
Summary: UNKNOWN
Home-page: https://github.com/nikialeksey/fpscanner
Author: Alexey Niktin
Author-email: nikialeksey@gmail.com
License: MIT
Platform: UNKNOWN
Classifier: License :: OSI Approved :: MIT License
Classifier: Operating System :: MacOS :: MacOS X
Classifier: Operating System :: POSIX
Classifier: Operating System :: POSIX :: BSD
Classifier: Operating System :: POSIX :: Linux
Classifier: Operating System :: Microsoft :: Windows
Classifier: Programming Language :: Python
Classifier: Programming Language :: Python :: 2
Classifier: Programming Language :: Python :: 2.7
Requires-Dist: Pillow (>=5.2.0)
Requires-Dist: pyserial (>=3.4)
